allauth/__init__.py
allauth/app_settings.py
allauth/conftest.py
allauth/decorators.py
allauth/exceptions.py
allauth/models.py
allauth/ratelimit.py
allauth/tests.py
allauth/urls.py
allauth/utils.py
allauth/account/__init__.py
allauth/account/adapter.py
allauth/account/admin.py
allauth/account/app_settings.py
allauth/account/apps.py
allauth/account/auth_backends.py
allauth/account/authentication.py
allauth/account/decorators.py
allauth/account/forms.py
allauth/account/managers.py
allauth/account/middleware.py
allauth/account/models.py
allauth/account/reauthentication.py
allauth/account/signals.py
allauth/account/stages.py
allauth/account/urls.py
allauth/account/utils.py
allauth/account/views.py
allauth/account/management/__init__.py
allauth/account/management/commands/__init__.py
allauth/account/management/commands/account_unsetmultipleprimaryemails.py
allauth/account/migrations/0001_initial.py
allauth/account/migrations/0002_email_max_length.py
allauth/account/migrations/0003_alter_emailaddress_create_unique_verified_email.py
allauth/account/migrations/0004_alter_emailaddress_drop_unique_email.py
allauth/account/migrations/0005_emailaddress_idx_upper_email.py
allauth/account/migrations/__init__.py
allauth/account/templatetags/__init__.py
allauth/account/templatetags/account.py
allauth/account/tests/__init__.py
allauth/account/tests/test_adapter.py
allauth/account/tests/test_ajax.py
allauth/account/tests/test_auth_backends.py
allauth/account/tests/test_change_email.py
allauth/account/tests/test_change_password.py
allauth/account/tests/test_commands.py
allauth/account/tests/test_confirm_email.py
allauth/account/tests/test_decorators.py
allauth/account/tests/test_login.py
allauth/account/tests/test_logout.py
allauth/account/tests/test_middleware.py
allauth/account/tests/test_models.py
allauth/account/tests/test_ratelimit.py
allauth/account/tests/test_reauthentication.py
allauth/account/tests/test_reset_password.py
allauth/account/tests/test_security.py
django_allauth_forked-0.61.0.dev0.dist-info/AUTHORS
django_allauth_forked-0.61.0.dev0.dist-info/LICENSE
django_allauth_forked-0.61.0.dev0.dist-info/METADATA
django_allauth_forked-0.61.0.dev0.dist-info/WHEEL
django_allauth_forked-0.61.0.dev0.dist-info/top_level.txt
django_allauth_forked-0.61.0.dev0.dist-info/RECORD
